many_versioned_wheel/__init__.py
many_versioned_wheel/version.py
many_versioned_wheel-0.2.1.dist-info/DESCRIPTION.rst
many_versioned_wheel-0.2.1.dist-info/METADATA
many_versioned_wheel-0.2.1.dist-info/RECORD
many_versioned_wheel-0.2.1.dist-info/WHEEL
many_versioned_wheel-0.2.1.dist-info/entry_points.txt
many_versioned_wheel-0.2.1.dist-info/metadata.json
many_versioned_wheel-0.2.1.dist-info/top_level.txt
