Metadata-Version: 2.0
Name: many-versioned-wheel
Version: 0.2.1
Summary: description: A library for testing stuff dealing with pypi packages
Home-page: UNKNOWN
Author: rschultheis
Author-email: justmakeanissueongithubpls@nothanks.org
License: MIT
Keywords: persistent identifiers
Platform: any
Requires-Dist: feedparser (==5.0.1)
